setup.cfg
setup.py
Alexandr_Varnakin/__init__.py
Alexandr_Varnakin/greeting.py
Alexandr_Varnakin/poslat_nahui.py
Alexandr_Varnakin.egg-info/PKG-INFO
Alexandr_Varnakin.egg-info/SOURCES.txt
Alexandr_Varnakin.egg-info/dependency_links.txt
Alexandr_Varnakin.egg-info/not-zip-safe
Alexandr_Varnakin.egg-info/top_level.txt