Metadata-Version: 2.1
Name: Alexandr-Varnakin
Version: 2.0
Summary: Coolest man on Earth
Author-email: mamadorogayamoskva@gmail.com
